setup.py
ShortestPathIntermediateStages/ShortestPathIntermediateStages.py
ShortestPathIntermediateStages/__init__.py
ShortestPathIntermediateStages.egg-info/PKG-INFO
ShortestPathIntermediateStages.egg-info/SOURCES.txt
ShortestPathIntermediateStages.egg-info/dependency_links.txt
ShortestPathIntermediateStages.egg-info/not-zip-safe
ShortestPathIntermediateStages.egg-info/top_level.txt