Metadata-Version: 1.0
Name: ShortestPathIntermediateStages
Version: 0.1
Summary: Shortest Path with Intermediate Stages
Home-page: UNKNOWN
Author: Luca Elias Schaefer
Author-email: UNKNOWN
License: UNKNOWN
Platform: UNKNOWN
